odoo/addons/account_move_payroll_import/CHANGELOG.md
odoo/addons/account_move_payroll_import/README.rst
odoo/addons/account_move_payroll_import/__init__.py
odoo/addons/account_move_payroll_import/__manifest__.py
odoo/addons/account_move_payroll_import/data/payroll_import_defaults.xml
odoo/addons/account_move_payroll_import/i18n/ca_ES.po
odoo/addons/account_move_payroll_import/i18n/es.po
odoo/addons/account_move_payroll_import/models/__init__.py
odoo/addons/account_move_payroll_import/models/payroll_custom_concept.py
odoo/addons/account_move_payroll_import/models/payroll_import_mapping.py
odoo/addons/account_move_payroll_import/models/payroll_import_setup.py
odoo/addons/account_move_payroll_import/security/ir.model.access.csv
odoo/addons/account_move_payroll_import/static/src/css/styles.css
odoo/addons/account_move_payroll_import/static/src/js/payroll_import_button.js
odoo/addons/account_move_payroll_import/static/src/xml/payroll_import_templates.xml
odoo/addons/account_move_payroll_import/utils/__init__.py
odoo/addons/account_move_payroll_import/utils/file_utils.py
odoo/addons/account_move_payroll_import/utils/parse_utils.py
odoo/addons/account_move_payroll_import/views/assets_template.xml
odoo/addons/account_move_payroll_import/views/payroll_import_views.xml
odoo/addons/account_move_payroll_import/wizards/__init__.py
odoo/addons/account_move_payroll_import/wizards/payroll_import_wizard.py
odoo/addons/account_move_payroll_import/wizards/payroll_import_wizard.xml
odoo12_addon_account_move_payroll_import-12.0.1.1.5.dist-info/METADATA
odoo12_addon_account_move_payroll_import-12.0.1.1.5.dist-info/WHEEL
odoo12_addon_account_move_payroll_import-12.0.1.1.5.dist-info/top_level.txt
odoo12_addon_account_move_payroll_import-12.0.1.1.5.dist-info/RECORD
