Metadata-Version: 2.1
Name: odoo12-addon-account-move-payroll-import
Version: 12.0.1.1.5
Summary: ODOO account move spanish payroll data import for social cooperatives.
Home-page: https://gitlab.com/somitcoop/erp-research/odoo-accounting
Author: Som It Cooperatiu SCCL, Som Connexió SCCL
License: AGPL-3
Platform: UNKNOWN
Classifier: Programming Language :: Python
Classifier: Framework :: Odoo
Classifier: Framework :: Odoo :: 12.0
Classifier: License :: OSI Approved :: GNU Affero General Public License v3
Requires-Python: >=3.5
Requires-Dist: odoo <12.1dev,>=12.0a
